langchain_huggingface/__init__.py
langchain_huggingface/chat_models/__init__.py
langchain_huggingface/chat_models/huggingface.py
langchain_huggingface/embeddings/__init__.py
langchain_huggingface/embeddings/huggingface.py
langchain_huggingface/embeddings/huggingface_endpoint.py
langchain_huggingface/llms/__init__.py
langchain_huggingface/llms/huggingface_endpoint.py
langchain_huggingface/llms/huggingface_pipeline.py
langchain_huggingface/py.typed
langchain_huggingface/tests/__init__.py
langchain_huggingface/tests/integration_tests/__init__.py
langchain_huggingface-0.1.1.dist-info/LICENSE
langchain_huggingface-0.1.1.dist-info/METADATA
langchain_huggingface-0.1.1.dist-info/WHEEL
langchain_huggingface-0.1.1.dist-info/RECORD
